MANIFEST.in
README.txt
setup.py
dist/ewb_case.casclient-0.1.1/README.txt
dist/ewb_case.casclient-0.1.1/setup.py
dist/ewb_case.casclient-0.1.1 2/README.txt
dist/ewb_case.casclient-0.1.1 2/setup.py
dist/ewb_case.casclient-0.1.1 2/dist/ewb_case.casclient-0.1.1/README.txt
dist/ewb_case.casclient-0.1.1 2/dist/ewb_case.casclient-0.1.1/setup.py
dist/ewb_case.casclient-0.1.1 2/dist/ewb_case.casclient-0.1.1/docs/HISTORY.txt
dist/ewb_case.casclient-0.1.1 2/dist/ewb_case.casclient-0.1.1/docs/INSTALL.txt
dist/ewb_case.casclient-0.1.1 2/dist/ewb_case.casclient-0.1.1/docs/LICENSE.GPL
dist/ewb_case.casclient-0.1.1 2/dist/ewb_case.casclient-0.1.1/docs/LICENSE.txt
dist/ewb_case.casclient-0.1.1 2/dist/ewb_case.casclient-0.1.1/ewb_case/__init__.py
dist/ewb_case.casclient-0.1.1 2/dist/ewb_case.casclient-0.1.1/ewb_case.casclient.egg-info/SOURCES.txt
dist/ewb_case.casclient-0.1.1 2/dist/ewb_case.casclient-0.1.1/ewb_case.casclient.egg-info/dependency_links.txt
dist/ewb_case.casclient-0.1.1 2/dist/ewb_case.casclient-0.1.1/ewb_case.casclient.egg-info/entry_points.txt
dist/ewb_case.casclient-0.1.1 2/dist/ewb_case.casclient-0.1.1/ewb_case.casclient.egg-info/namespace_packages.txt
dist/ewb_case.casclient-0.1.1 2/dist/ewb_case.casclient-0.1.1/ewb_case.casclient.egg-info/requires.txt
dist/ewb_case.casclient-0.1.1 2/dist/ewb_case.casclient-0.1.1/ewb_case.casclient.egg-info/top_level.txt
dist/ewb_case.casclient-0.1.1 2/dist/ewb_case.casclient-0.1.1/ewb_case/casclient/__init__.py
dist/ewb_case.casclient-0.1.1 2/dist/ewb_case.casclient-0.1.1/ewb_case/casclient/configure.zcml
dist/ewb_case.casclient-0.1.1 2/dist/ewb_case.casclient-0.1.1/ewb_case/casclient/install.py
dist/ewb_case.casclient-0.1.1 2/dist/ewb_case.casclient-0.1.1/ewb_case/casclient/profiles.zcml
dist/ewb_case.casclient-0.1.1 2/dist/ewb_case.casclient-0.1.1/ewb_case/casclient/tests.py
dist/ewb_case.casclient-0.1.1 2/dist/ewb_case.casclient-0.1.1/ewb_case/casclient/version.txt
dist/ewb_case.casclient-0.1.1 2/dist/ewb_case.casclient-0.1.1/ewb_case/casclient/browser/__init__.py
dist/ewb_case.casclient-0.1.1 2/dist/ewb_case.casclient-0.1.1/ewb_case/casclient/browser/caslogin.py
dist/ewb_case.casclient-0.1.1 2/dist/ewb_case.casclient-0.1.1/ewb_case/casclient/browser/caslogout.py
dist/ewb_case.casclient-0.1.1 2/dist/ewb_case.casclient-0.1.1/ewb_case/casclient/browser/configure.zcml
dist/ewb_case.casclient-0.1.1 2/dist/ewb_case.casclient-0.1.1/ewb_case/casclient/browser/templates/add_cas_client_form.pt
dist/ewb_case.casclient-0.1.1 2/dist/ewb_case.casclient-0.1.1/ewb_case/casclient/plugins/__init__.py
dist/ewb_case.casclient-0.1.1 2/ewb_case.casclient.egg-info/SOURCES.txt
dist/ewb_case.casclient-0.1.1 2/ewb_case.casclient.egg-info/dependency_links.txt
dist/ewb_case.casclient-0.1.1 2/ewb_case.casclient.egg-info/entry_points.txt
dist/ewb_case.casclient-0.1.1 2/ewb_case.casclient.egg-info/namespace_packages.txt
dist/ewb_case.casclient-0.1.1 2/ewb_case.casclient.egg-info/requires.txt
dist/ewb_case.casclient-0.1.1 2/ewb_case.casclient.egg-info/top_level.txt
dist/ewb_case.casclient-0.1.1/ewb_case.casclient.egg-info/SOURCES.txt
dist/ewb_case.casclient-0.1.1/ewb_case.casclient.egg-info/dependency_links.txt
dist/ewb_case.casclient-0.1.1/ewb_case.casclient.egg-info/entry_points.txt
dist/ewb_case.casclient-0.1.1/ewb_case.casclient.egg-info/namespace_packages.txt
dist/ewb_case.casclient-0.1.1/ewb_case.casclient.egg-info/requires.txt
dist/ewb_case.casclient-0.1.1/ewb_case.casclient.egg-info/top_level.txt
ewb_case.casclient.egg-info/PKG-INFO
ewb_case.casclient.egg-info/SOURCES.txt
ewb_case.casclient.egg-info/dependency_links.txt
ewb_case.casclient.egg-info/entry_points.txt
ewb_case.casclient.egg-info/namespace_packages.txt
ewb_case.casclient.egg-info/not-zip-safe
ewb_case.casclient.egg-info/requires.txt
ewb_case.casclient.egg-info/top_level.txt
