Metadata-Version: 1.0
Name: ewb-case.casclient
Version: 0.1.3
Summary: Provides CAS authentication for EWB Case website.
Home-page: https://github.com/mattbierner/ewb_case.casclient
Author: Matt Bierner
Author-email: mattbierner@gmail.com
License: GPL
Platform: UNKNOWN
Classifier: Framework :: Plone
Classifier: Programming Language :: Python
